{
  "reinhard-ernst-museum": {
    "cover_url": "/images/curated/reinhard-ernst-museum-1024.jpg",
    "cover_photographer": "Gerda Arendt",
    "cover_license": "CC0",
    "cover_source_url": "https://commons.wikimedia.org/wiki/File:Ernst_Museum,_Wiesbaden,_atrium.jpg"
  },
  "marsk-tower": {
    "cover_url": "/images/curated/marsk-tower-1024.jpg",
    "cover_photographer": "Elgaard",
    "cover_license": "CC BY-SA 4.0",
    "cover_source_url": "https://commons.wikimedia.org/wiki/File%3AMarsk_Tower_lookout_01.jpg"
  },
  "one-monte-carlo": {
    "cover_url": "/images/curated/one-monte-carlo-1024.jpg",
    "cover_photographer": "Renek78",
    "cover_license": "CC BY-SA 4.0",
    "cover_source_url": "https://commons.wikimedia.org/wiki/File:One_Monte_Carlo_at_night_in_July_2020.jpg"
  },
  "q118539028": {
    "cover_url": "/images/curated/q118539028-1024.jpg",
    "cover_photographer": "Bextrel",
    "cover_license": "CC BY 4.0",
    "cover_source_url": "https://commons.wikimedia.org/wiki/File:Capela_do_Monte,_Barao_de_Sao_Joao_1_-_Algarve,_Portugal_-_27.01.2024.jpg"
  },
  "parc1": {
    "cover_url": "/images/curated/parc1-1024.jpg",
    "cover_photographer": "Tony",
    "cover_license": "CC BY 2.0",
    "cover_source_url": "https://commons.wikimedia.org/wiki/File:Dangsan_Railway_Bridge_Morning_View.jpg"
  },
  "copenhill": {
    "cover_url": "/images/curated/copenhill-1024.jpg",
    "cover_photographer": "kallerna",
    "cover_license": "CC BY-SA 4.0",
    "cover_source_url": "https://commons.wikimedia.org/wiki/File:Copenhill_5.jpg"
  },
  "james-simon-gallery": {
    "cover_url": "/images/curated/james-simon-gallery-1024.jpg",
    "cover_photographer": "Gunnar Klack",
    "cover_license": "CC BY-SA 4.0",
    "cover_source_url": "https://commons.wikimedia.org/wiki/File:2019-04-26-James-Simon-Galerie.jpg"
  },
  "torres-atrio": {
    "cover_url": "/images/curated/torres-atrio-1024.jpg",
    "cover_photographer": "EEIM",
    "cover_license": "CC BY-SA 4.0",
    "cover_source_url": "https://commons.wikimedia.org/wiki/File:2018_agst_Torres_Atrio_de_Bogot%C3%A1_-_1.jpeg"
  },
  "l-arbre-blanc": {
    "cover_url": "/images/curated/l-arbre-blanc-1024.jpg",
    "cover_photographer": "Bruno Barral",
    "cover_license": "CC BY-SA 4.0",
    "cover_source_url": "https://commons.wikimedia.org/wiki/File%3ALArbreBlancEtLeLez.jpg"
  },
  "beijing-daxing-airport": {
    "cover_url": "/images/curated/beijing-daxing-airport-1024.jpg",
    "cover_photographer": "Tyg728",
    "cover_license": "CC BY-SA 4.0",
    "cover_source_url": "https://commons.wikimedia.org/wiki/File:Interior_of_Beijing_Daxing_International_Airport_20191005.jpg"
  },
  "national-stadium-tokyo": {
    "cover_url": "/images/curated/national-stadium-tokyo-1024.jpg",
    "cover_photographer": "Akonnchiroll",
    "cover_license": "CC BY 4.0",
    "cover_source_url": "https://commons.wikimedia.org/wiki/File:Japan_National_Stadium_2024_1.jpg"
  },
  "mt-fuji-center": {
    "cover_url": "/images/curated/mt-fuji-center-1024.jpg",
    "cover_photographer": "Ennui",
    "cover_license": "CC BY-SA 4.0",
    "cover_source_url": "https://commons.wikimedia.org/wiki/File%3AMt.fuji_World_Heritage_Centre%2CShizuoka.jpg"
  },
  "dongdaemun-design-plaza": {
    "cover_url": "/images/curated/dongdaemun-design-plaza-1024.jpg",
    "cover_photographer": "Korea",
    "cover_license": "CC BY-SA 4.0",
    "cover_source_url": "https://commons.wikimedia.org/wiki/File:Dongdaemun_Design_Plaza_at_night,_Seoul,_Korea.jpg"
  },
  "asakusa-culture-center": {
    "cover_url": "/images/curated/asakusa-culture-center-1024.jpg",
    "cover_photographer": "Kakidai",
    "cover_license": "CC BY-SA 3.0",
    "cover_source_url": "https://commons.wikimedia.org/wiki/File%3AAsakusa_Culture_Tourism_Center.JPG"
  },
  "gckeyaki-terrace": {
    "cover_url": "/images/curated/gckeyaki-terrace-1024.jpg",
    "cover_photographer": "Guilhem Vellut",
    "cover_license": "CC BY 2.0",
    "cover_source_url": "https://commons.wikimedia.org/wiki/File:Tokyo_Midtown_(11420987086).jpg"
  },
  "whitney-museum": {
    "cover_url": "/images/curated/whitney-museum-1024.jpg",
    "cover_photographer": "Kidfly182",
    "cover_license": "CC BY 4.0",
    "cover_source_url": "https://commons.wikimedia.org/wiki/File:Whitney_Museum_of_American_Art_August_2024.jpg"
  },
  "aspen-art-museum": {
    "cover_url": "/images/curated/aspen-art-museum-1024.jpg",
    "cover_photographer": "Bkthomson16",
    "cover_license": "CC BY-SA 4.0",
    "cover_source_url": "https://commons.wikimedia.org/wiki/File:Aspen_Art_Museum_by_Shigeru_Ban.jpg"
  },
  "louis-vuitton-fondation": {
    "cover_url": "/images/curated/louis-vuitton-fondation-1024.jpg",
    "cover_photographer": "Tosek",
    "cover_license": "CC BY-SA 4.0",
    "cover_source_url": "https://commons.wikimedia.org/wiki/File:Fondation_Louis_Vuitton_20160413_South_01.jpg"
  },
  "cardboard-cathedral": {
    "cover_url": "/images/curated/cardboard-cathedral-1024.jpg",
    "cover_photographer": "Michal Klajban",
    "cover_license": "CC BY-SA 4.0",
    "cover_source_url": "https://commons.wikimedia.org/wiki/File:Cardboard_Cathedral,_Christchurch,_New_Zealand.jpg"
  },
  "cctv-headquarters": {
    "cover_url": "/images/curated/cctv-headquarters-1024.jpg",
    "cover_photographer": "CNHowey",
    "cover_license": "CC0",
    "cover_source_url": "https://commons.wikimedia.org/wiki/File:Beijing_CCTV_building.jpg"
  },
  "museu-de-arte-contemporanea-nadir": {
    "cover_url": "/images/curated/museu-de-arte-contemporanea-nadir-1024.jpg",
    "cover_photographer": "Ad narragoniam",
    "cover_license": "CC BY-SA 4.0",
    "cover_source_url": "https://commons.wikimedia.org/wiki/File:Ema_Berta_Expo_MACNA_2018_a.jpg"
  },
  "lego-house": {
    "cover_url": "/images/curated/lego-house-1024.jpg",
    "cover_photographer": null,
    "cover_license": "CC BY-SA",
    "cover_source_url": "https://upload.wikimedia.org/wikipedia/commons/8/8a/Lego_House_Billund.jpg/Lego_House_Billund.jpg"
  },
  "guggenheim-bilbao": {
    "cover_url": "/images/curated/guggenheim-bilbao-1024.jpg",
    "cover_photographer": "Fred Romero",
    "cover_license": "CC BY 2.0",
    "cover_source_url": "https://commons.wikimedia.org/wiki/File:Museo_Guggenheim,_Bilbao_(31273245344).jpg"
  },
  "fallingwater": {
    "cover_url": "/images/curated/fallingwater-1024.jpg",
    "cover_photographer": "Sxenko",
    "cover_license": "CC BY-SA 3.0",
    "cover_source_url": "https://commons.wikimedia.org/wiki/File:Fallingwater_2007.jpg"
  },
  "barcelona-pavilion": {
    "cover_url": "/images/curated/barcelona-pavilion-1024.jpg",
    "cover_photographer": "Ashley Pomeroy",
    "cover_license": "CC BY-SA 3.0",
    "cover_source_url": "https://commons.wikimedia.org/wiki/File:The_Barcelona_Pavilion,_Barcelona,_2010.jpg"
  },
  "sagrada-familia": {
    "cover_url": "/images/curated/sagrada-familia-1024.jpg",
    "cover_photographer": "Bernard Gagnon",
    "cover_license": "CC BY-SA 3.0",
    "cover_source_url": "https://commons.wikimedia.org/wiki/File:Sagrada_Familia_01.jpg"
  },
  "st-pauls-cathedral": {
    "cover_url": "/images/curated/st-pauls-cathedral-1024.jpg",
    "cover_photographer": "Mark",
    "cover_license": "CC BY-SA 3.0",
    "cover_source_url": "https://commons.wikimedia.org/wiki/File:St_Pauls_aerial_(cropped).jpg"
  },
  "seattle-central-library": {
    "cover_url": "/images/curated/seattle-central-library-1024.jpg",
    "cover_photographer": "J. Miers",
    "cover_license": "CC BY-SA 3.0",
    "cover_source_url": "https://commons.wikimedia.org/wiki/File:Seattle_Central_Library,_Seattle,_Washington_-_20060418.jpg"
  },
  "tate-modern": {
    "cover_url": "/images/curated/tate-modern-1024.jpg",
    "cover_photographer": "Duncan",
    "cover_license": "CC BY-SA 3.0",
    "cover_source_url": "https://commons.wikimedia.org/wiki/File:Tate_Modern_-_Bankside_Power_Station.jpg"
  },
  "lloyds-building": {
    "cover_url": "/images/curated/lloyds-building-1024.jpg",
    "cover_photographer": "Robert Rimell",
    "cover_license": "CC BY-SA 2.0",
    "cover_source_url": "https://commons.wikimedia.org/wiki/File:%22The_Gherkin%22_and_Lloyds_Building_-_geograph.org.uk_-_2117382.jpg"
  },
  "casa-mila": {
    "cover_url": "/images/curated/casa-mila-1024.jpg",
    "cover_photographer": "Thomas Ledl",
    "cover_license": "CC BY-SA 3.0",
    "cover_source_url": "https://commons.wikimedia.org/wiki/File:Casa_Mil%C3%A0,_general_view.jpg"
  },
  "apple-park": {
    "cover_url": "/images/curated/apple-park-1024.jpg",
    "cover_photographer": "Daniel L. Lu (user:dllu)",
    "cover_license": "CC BY-SA 4.0",
    "cover_source_url": "https://commons.wikimedia.org/wiki/File:Aerial_view_of_Apple_Park.jpg"
  },
  "walt-disney-concert-hall": {
    "cover_url": "/images/curated/walt-disney-concert-hall-1024.jpg",
    "cover_photographer": "Benoît Prieur",
    "cover_license": "CC0",
    "cover_source_url": "https://commons.wikimedia.org/wiki/File:Walt_Disney_Concert_Hall_July_2022.JPG"
  },
  "dancing-house": {
    "cover_url": "/images/curated/dancing-house-1024.jpg",
    "cover_photographer": "Maros M r a z (Maros)",
    "cover_license": "CC BY-SA 3.0",
    "cover_source_url": "https://commons.wikimedia.org/wiki/File:Prague_-_Dancing_House.jpg"
  },
  "sydney-opera-house": {
    "cover_url": "/images/curated/sydney-opera-house-1024.jpg",
    "cover_photographer": "wilford peloquin",
    "cover_license": "CC BY 2.0",
    "cover_source_url": "https://commons.wikimedia.org/wiki/File:174_Sydney_Aug_1976_(51747972351).jpg"
  },
  "villa-savoye": {
    "cover_url": "/images/curated/villa-savoye-1024.jpg",
    "cover_photographer": "Pascal3012",
    "cover_license": "CC BY-SA 4.0",
    "cover_source_url": "https://commons.wikimedia.org/wiki/File:Ville-Savoye.JPG"
  },
  "salk-institute": {
    "cover_url": "/images/curated/salk-institute-1024.jpg",
    "cover_photographer": "Cristina Bejarano",
    "cover_license": "CC BY 2.0",
    "cover_source_url": "https://commons.wikimedia.org/wiki/File:Salk_institute_2014.jpg"
  },
  "3-world-trade-center": {
    "cover_url": "/images/curated/3-world-trade-center-1024.jpg",
    "cover_photographer": "Famartin",
    "cover_license": "CC BY-SA 4.0",
    "cover_source_url": "https://commons.wikimedia.org/wiki/File:2024-06-15_08_38_00_View_west_towards_Lower_Manhattan_from_the_middle_of_the_Brooklyn_Bridge_along_the_border_of_Manhattan_and_Brooklyn_in_New_York_City,_New_York.jpg"
  },
  "122-leadenhall-street": {
    "cover_url": "/images/curated/122-leadenhall-street-1024.jpg",
    "cover_photographer": "Leena Nath",
    "cover_license": "CC BY 3.0",
    "cover_source_url": "https://commons.wikimedia.org/wiki/File:%22The_Cheesegrater%22_122_Leadenhall_Street_London._Designed_by_Rogers_Stirk_Harbour_%2B_Partners_1.jpg"
  },
  "8-house": {
    "cover_url": "/images/curated/8-house-1024.jpg",
    "cover_photographer": "Fred Romero",
    "cover_license": "CC BY 2.0",
    "cover_source_url": "https://commons.wikimedia.org/wiki/File:K%C3%B8benhavn_-_8Tallet_(30882786402).jpg"
  },
  "88-wood-street": {
    "cover_url": "/images/curated/88-wood-street-1024.jpg",
    "cover_photographer": "Steve Cadman",
    "cover_license": "CC BY-SA 2.0",
    "cover_source_url": "https://commons.wikimedia.org/wiki/File:88_Wood_St_by_Graham_Stirk_of_Richard_Rogers_Partnership.jpg"
  },
  "945-madison-avenue": {
    "cover_url": "/images/curated/945-madison-avenue-1024.jpg",
    "cover_photographer": "WPA employee",
    "cover_license": "Public domain",
    "cover_source_url": "https://commons.wikimedia.org/wiki/File:Site_of_Breuer_Building,_1940s.jpg"
  },
  "190-192-sloane-street": {
    "cover_url": "/images/curated/190-192-sloane-street-1024.jpg",
    "cover_photographer": "Paul the Archivist",
    "cover_license": "CC BY-SA 4.0",
    "cover_source_url": "https://commons.wikimedia.org/wiki/File:190-192_Sloane_St,_London.jpg"
  },
  "4-world-trade-center": {
    "cover_url": "/images/curated/4-world-trade-center-1024.jpg",
    "cover_photographer": "Lars Plougmann from United Kingdom",
    "cover_license": "CC BY-SA 2.0",
    "cover_source_url": "https://commons.wikimedia.org/wiki/File:22_Cortlandt_Street_One_Liberty_Plaza_from_2WTC_1984.jpg"
  },
  "51-astor-place": {
    "cover_url": "/images/curated/51-astor-place-1024.jpg",
    "cover_photographer": "Eden, Janine and Jim from New York City",
    "cover_license": "CC BY 2.0",
    "cover_source_url": "https://commons.wikimedia.org/wiki/File:51_Astor_at_Night_(8502346496).jpg"
  },
  "aga-khan-museum": {
    "cover_url": "/images/curated/aga-khan-museum-1024.jpg",
    "cover_photographer": "Faisal Anwar",
    "cover_license": "CC BY-SA 4.0",
    "cover_source_url": "https://commons.wikimedia.org/wiki/File:01SensoryGardenCharBagh.jpg"
  },
  "acropolis-museum": {
    "cover_url": "/images/curated/acropolis-museum-1024.jpg",
    "cover_photographer": "Holger Uwe Schmitt",
    "cover_license": "CC BY-SA 4.0",
    "cover_source_url": "https://commons.wikimedia.org/wiki/File:%22Ausschlie%C3%9Flich_Fundst%C3%BCcke_und_Objekte_von_der_Akropolis_von_Athen%22_werden_hier_ausgestellt._03.jpg"
  },
  "americas-cup-building": {
    "cover_url": "/images/curated/americas-cup-building-1024.jpg",
    "cover_photographer": "Yasuhiro Chatani from Tokyo, Japan",
    "cover_license": "CC BY 2.0",
    "cover_source_url": "https://commons.wikimedia.org/wiki/File:33rd_America%27s_Cup_inauguration_act_(4339971114).jpg"
  },
  "alvar-aalto-museum-jyvaskyla": {
    "cover_url": "/images/curated/alvar-aalto-museum-jyvaskyla-1024.jpg",
    "cover_photographer": "Mikkoau",
    "cover_license": "CC BY-SA 4.0",
    "cover_source_url": "https://commons.wikimedia.org/wiki/File:Alvar_Aalto_-museo_Jyv%C3%A4skyl%C3%A4.jpg"
  },
  "aalto-hochhaus": {
    "cover_url": "/images/curated/aalto-hochhaus-1024.jpg",
    "cover_photographer": "VReporter (talk)",
    "cover_license": "CC BY-SA 4.0",
    "cover_source_url": "https://commons.wikimedia.org/wiki/File:Aalto_4_seiten.png"
  },
  "aarhus-city-hall": {
    "cover_url": "/images/curated/aarhus-city-hall-1024.jpg",
    "cover_photographer": "Unknown authorUnknown author",
    "cover_license": "Public domain",
    "cover_source_url": "https://commons.wikimedia.org/wiki/File:01_Aarhus_R%C3%A5dhus,_ca_1950_f%2B.jpg"
  },
  "aaltoalvari": {
    "cover_url": "/images/curated/aaltoalvari-1024.jpg",
    "cover_photographer": "Tiia Monto",
    "cover_license": "CC BY-SA 4.0",
    "cover_source_url": "https://commons.wikimedia.org/wiki/File:AaltoAlvari_2018.jpg"
  },
  "ameritrust-tower": {
    "cover_url": "/images/curated/ameritrust-tower-1024.jpg",
    "cover_photographer": "NorthCoastReader",
    "cover_license": "CC BY-SA 3.0",
    "cover_source_url": "https://commons.wikimedia.org/wiki/File:Ameritrust_Tower.JPG"
  },
  "arenas-de-barcelona": {
    "cover_url": "/images/curated/arenas-de-barcelona-1024.jpg",
    "cover_photographer": "Enric",
    "cover_license": "CC BY-SA 4.0",
    "cover_source_url": "https://commons.wikimedia.org/wiki/File:002_Dona_i_ocell,_parc_de_Joan_Mir%C3%B3_(Barcelona),_al_fons_la_pla%C3%A7a_de_les_Arenes.jpg"
  },
  "apa-hotel-resort-tokyo-bay": {
    "cover_url": "/images/curated/apa-hotel-resort-tokyo-bay-1024.jpg",
    "cover_photographer": "resource70",
    "cover_license": "CC BY 3.0",
    "cover_source_url": "https://commons.wikimedia.org/wiki/File:20070922_P9220738_1600_-_panoramio.jpg"
  },
  "arne-jacobsen-bau-in-mainz-hartenberg-munchfeld": {
    "cover_url": "/images/curated/arne-jacobsen-bau-in-mainz-hartenberg-munchfeld-1024.jpg",
    "cover_photographer": "Symposiarch",
    "cover_license": "CC BY 3.0",
    "cover_source_url": "https://commons.wikimedia.org/wiki/File:NovoMainzJacobsen1.JPG"
  },
  "ariston-club": {
    "cover_url": "/images/curated/ariston-club-1024.jpg",
    "cover_photographer": "Flipwared",
    "cover_license": "CC BY-SA 4.0",
    "cover_source_url": "https://commons.wikimedia.org/wiki/File:Ariston_2.jpg"
  },
  "ashford-designer-outlet": {
    "cover_url": "/images/curated/ashford-designer-outlet-1024.jpg",
    "cover_photographer": "terry joyce",
    "cover_license": "CC BY-SA 2.0",
    "cover_source_url": "https://commons.wikimedia.org/wiki/File:Aerial_view_of_Ashford_-_geograph.org.uk_-_575124.jpg"
  },
  "arthur-and-mona-hofmann-house": {
    "cover_url": "/images/curated/arthur-and-mona-hofmann-house-1024.jpg",
    "cover_photographer": "Sanfranman59",
    "cover_license": "CC BY-SA 3.0",
    "cover_source_url": "https://commons.wikimedia.org/wiki/File:Arthur_and_Mona_Hofmann_House,_1048_La_Cuesta_Rd.,_Hillsborough,_CA_9-5-2011_3-14-45_PM.JPG"
  },
  "asian-arts-museum": {
    "cover_url": "/images/curated/asian-arts-museum-1024.jpg",
    "cover_photographer": "Dominique Legros",
    "cover_license": "CC BY 3.0",
    "cover_source_url": "https://commons.wikimedia.org/wiki/File:Arenas_Nice_(4798821).jpeg"
  },
  "assumption-of-mary-cathedral-hiroshima": {
    "cover_url": "/images/curated/assumption-of-mary-cathedral-hiroshima-1024.jpg",
    "cover_photographer": "Uhooep",
    "cover_license": "CC BY-SA 4.0",
    "cover_source_url": "https://commons.wikimedia.org/wiki/File:Assumption_of_Mary_Cathedral,_Hiroshima.jpg"
  },
  "asilo-santelia": {
    "cover_url": "/images/curated/asilo-santelia-1024.jpg",
    "cover_photographer": "Agnese Cetti",
    "cover_license": "CC BY-SA 4.0",
    "cover_source_url": "https://commons.wikimedia.org/wiki/File:Asilo_sant%27elia_007.jpg"
  },
  "atelier-museu-julio-pomar": {
    "cover_url": "/images/curated/atelier-museu-julio-pomar-1024.jpg",
    "cover_photographer": "Pedro Ribeiro Simões from Lisboa, Portugal",
    "cover_license": "CC BY 2.0",
    "cover_source_url": "https://commons.wikimedia.org/wiki/File:A_typical_Lisbon_street_(31699517028).jpg"
  },
  "atlanta-fulton-county-central-library": {
    "cover_url": "/images/curated/atlanta-fulton-county-central-library-1024.jpg",
    "cover_photographer": "JJonahJackalope",
    "cover_license": "CC BY-SA 4.0",
    "cover_source_url": "https://commons.wikimedia.org/wiki/File:Atlanta_Central_Library_2.jpg"
  },
  "auditorium-building": {
    "cover_url": "/images/curated/auditorium-building-1024.jpg",
    "cover_photographer": "J. Crocker",
    "cover_license": "CC BY-SA 3.0",
    "cover_source_url": "https://commons.wikimedia.org/wiki/File:Auditorium_Building_Chicago.jpg"
  },
  "atocha-cercanias": {
    "cover_url": "/images/curated/atocha-cercanias-1024.jpg",
    "cover_photographer": "M.Peinado from Alcalá de Henares, España",
    "cover_license": "CC BY 2.0",
    "cover_source_url": "https://commons.wikimedia.org/wiki/File:000414_-_Madrid_(2863719776).jpg"
  },
  "audrey-jones-beck-building": {
    "cover_url": "/images/curated/audrey-jones-beck-building-1024.jpg",
    "cover_photographer": "WhisperToMe",
    "cover_license": "CC0",
    "cover_source_url": "https://commons.wikimedia.org/wiki/File:Audrey_Jones_Beck_Building,_Museum_of_Fine_Arts,_Houston.jpg"
  },
  "elbphilharmonie": {
    "cover_url": "/images/curated/elbphilharmonie-1024.jpg",
    "cover_photographer": "Der Wolf im Wald",
    "cover_license": "CC BY-SA 3.0 de",
    "cover_source_url": "https://commons.wikimedia.org/wiki/File:Elbphilharmonie_Hamburg.jpg"
  },
  "bagsv-rd-church": {
    "cover_url": "/images/curated/bagsv-rd-church-1024.jpg",
    "cover_photographer": "No machine-readable author provided. Troels Eske assumed (based on copyright claims).",
    "cover_license": "CC BY-SA 3.0",
    "cover_source_url": "https://commons.wikimedia.org/wiki/File:Bagsv1.JPG"
  },
  "australia-square": {
    "cover_url": "/images/curated/australia-square-1024.jpg",
    "cover_photographer": "Sardaka",
    "cover_license": "CC BY-SA 3.0",
    "cover_source_url": "https://commons.wikimedia.org/wiki/File:(1)Australia_Square-1.jpg"
  },
  "bairro-da-malagueira": {
    "cover_url": "/images/curated/bairro-da-malagueira-1024.jpg",
    "cover_photographer": "Torchondo from Sevilla, España",
    "cover_license": "CC BY 2.0",
    "cover_source_url": "https://commons.wikimedia.org/wiki/File:Bairro_Malagueira_1_(Evora).jpg"
  },
  "va-dundee": {
    "cover_url": "/images/curated/va-dundee-1024.jpg",
    "cover_photographer": "GeographBot",
    "cover_license": "CC BY-SA 2.0",
    "cover_source_url": "https://commons.wikimedia.org/wiki/File:The_V%5EA_Museum,_Dundee_-_geograph.org.uk_-_5915039.jpg"
  },
  "bank-leumi-building-jerusalem": {
    "cover_url": "/images/curated/bank-leumi-building-jerusalem-1024.jpg",
    "cover_photographer": "Danny Gershoni",
    "cover_license": "CC BY-SA 4.0",
    "cover_source_url": "https://commons.wikimedia.org/wiki/File:Anglo-Palestine_bank_-_Bank_Leumi_-_Jerusalem_1.jpg"
  },
  "banca-popolare-di-verona": {
    "cover_url": "/images/curated/banca-popolare-di-verona-1024.jpg",
    "cover_photographer": "Mateus2019",
    "cover_license": "CC BY-SA 3.0",
    "cover_source_url": "https://commons.wikimedia.org/wiki/File:2021_%E2%80%94_Erste_Julireise_Mateus2019_%E2%80%94_Batch_(208).jpg"
  },
  "bank-of-china-tower": {
    "cover_url": "/images/curated/bank-of-china-tower-1024.jpg",
    "cover_photographer": "Wing1990hk",
    "cover_license": "CC BY-SA 3.0",
    "cover_source_url": "https://commons.wikimedia.org/wiki/File:Bank_of_China_Tower.jpg"
  },
  "bank-melli-iran-university-of": {
    "cover_url": "/images/curated/bank-melli-iran-university-of-1024.jpg",
    "cover_photographer": "seier+seier",
    "cover_license": "CC BY 2.0",
    "cover_source_url": "https://commons.wikimedia.org/wiki/File:J%C3%B8rn_utzon,_bank_melli,_tehran,_iran_1959-1962._model..jpg"
  },
  "bank-of-shanghai-headquarters": {
    "cover_url": "/images/curated/bank-of-shanghai-headquarters-1024.jpg",
    "cover_photographer": "Baycrest",
    "cover_license": "CC BY-SA 2.5",
    "cover_source_url": "https://commons.wikimedia.org/wiki/File:Bank_of_Shanghai_Headquarters.jpg"
  },
  "bank-of-spain-building-in": {
    "cover_url": "/images/curated/bank-of-spain-building-in-1024.jpg",
    "cover_photographer": "Kordas",
    "cover_license": "CC BY-SA 3.0",
    "cover_source_url": "https://commons.wikimedia.org/wiki/File:Banco_de_Espa%C3%B1a_de_Ja%C3%A9n.jpg"
  },
  "bankinter-building": {
    "cover_url": "/images/curated/bankinter-building-1024.jpg",
    "cover_photographer": "Luis García (Zaqarbal)",
    "cover_license": "CC BY-SA 3.0 es",
    "cover_source_url": "https://commons.wikimedia.org/wiki/File:Edificio_Bankinter_(Madrid)_01.jpg"
  },
  "bank-of-spain-headquarters": {
    "cover_url": "/images/curated/bank-of-spain-headquarters-1024.jpg",
    "cover_photographer": "Desconocido (Publicada por Léon &amp; Lévy)",
    "cover_license": "Public domain",
    "cover_source_url": "https://commons.wikimedia.org/wiki/File:Madrid,_postales_251.jpg"
  },
  "pompidou-centre": {
    "cover_url": "/images/curated/pompidou-centre-1024.jpg",
    "cover_photographer": "DiscoA340",
    "cover_license": "CC BY-SA 4.0",
    "cover_source_url": "https://commons.wikimedia.org/wiki/File:View_from_the_Centre_Pompidou_2.jpg"
  },
  "burj-khalifa": {
    "cover_url": "/images/curated/burj-khalifa-1024.jpg",
    "cover_photographer": "Laika ac",
    "cover_license": "CC BY-SA 2.0",
    "cover_source_url": "https://commons.wikimedia.org/wiki/File:Burj_Khalifa_(16260269606).jpg"
  },
  "empire-state-building": {
    "cover_url": "/images/curated/empire-state-building-1024.jpg",
    "cover_photographer": "Daniel Schwen",
    "cover_license": "CC BY-SA 4.0",
    "cover_source_url": "https://commons.wikimedia.org/wiki/File:Empire_State_Building_pano.jpg"
  },
  "taj-mahal": {
    "cover_url": "/images/curated/taj-mahal-1024.jpg",
    "cover_photographer": "Yann / King of Hearts",
    "cover_license": "CC BY-SA 4.0",
    "cover_source_url": "https://commons.wikimedia.org/wiki/File:Taj_Mahal,_Agra,_India_edit2.jpg"
  },
  "barack-obama-presidential-center": {
    "cover_url": "/images/curated/barack-obama-presidential-center-1024.jpg",
    "cover_photographer": "Barack Obama Presidential Center",
    "cover_license": "Public domain",
    "cover_source_url": "https://commons.wikimedia.org/wiki/File:3D_Rendering_of_the_Barack_Obama_Presidential_Center.png"
  },
  "colosseum": {
    "cover_url": "/images/curated/colosseum-1024.jpg",
    "cover_photographer": "Diliff",
    "cover_license": "CC BY-SA 2.5",
    "cover_source_url": "https://commons.wikimedia.org/wiki/File:Colosseum_in_Rome,_Italy_-_April_2007.jpg"
  },
  "basilica-palladiana": {
    "cover_url": "/images/curated/basilica-palladiana-1024.jpg",
    "cover_photographer": null,
    "cover_license": "CC BY-SA",
    "cover_source_url": "https://upload.wikimedia.org/wikipedia/commons/7/73/Basilica_Palladiana_Vicenza.jpg/Basilica_Palladiana_Vicenza.jpg"
  },
  "basilica-fano": {
    "cover_url": "/images/curated/basilica-fano-1024.jpg",
    "cover_photographer": "Cesare Cesariano",
    "cover_license": "Public domain",
    "cover_source_url": "https://commons.wikimedia.org/wiki/File%3ACesare_Cesariano%2C_Basilika_von_Fano%2C_Entwurf.jpg"
  },
  "beijing-national-stadium": {
    "cover_url": "/images/curated/beijing-national-stadium-1024.jpg",
    "cover_photographer": "Peter23",
    "cover_license": "CC BY-SA 2.0",
    "cover_source_url": "https://commons.wikimedia.org/wiki/File:Beijing_national_stadium.jpg"
  },
  "bauhaus-dessau": {
    "cover_url": "/images/curated/bauhaus-dessau-1024.jpg",
    "cover_photographer": "Thomas",
    "cover_license": "CC BY-SA 4.0",
    "cover_source_url": "https://commons.wikimedia.org/wiki/File:Bauhaus_Dessau_2018.jpg"
  },
  "beinecke-rare-book-manuscript-library": {
    "cover_url": "/images/curated/beinecke-rare-book-manuscript-library-1024.jpg",
    "cover_photographer": "Beinecke Library",
    "cover_license": "CC BY-SA 2.0",
    "cover_source_url": "https://commons.wikimedia.org/wiki/File:1960s_Yale_5062811384_card_catalog.jpg"
  },
  "bellavista-housing-estate": {
    "cover_url": "/images/curated/bellavista-housing-estate-1024.jpg",
    "cover_photographer": "©Hans Andersen",
    "cover_license": "CC BY-SA 3.0",
    "cover_source_url": "https://commons.wikimedia.org/wiki/File:Arne_Jacobsen_Bellavista_2005-01.jpg"
  },
  "bellevue-arts-museum": {
    "cover_url": "/images/curated/bellevue-arts-museum-1024.jpg",
    "cover_photographer": "Another Believer",
    "cover_license": "CC BY-SA 4.0",
    "cover_source_url": "https://commons.wikimedia.org/wiki/File:Bellevue,_WA_(2023)_-_54.jpg"
  },
  "bellevue-teatret": {
    "cover_url": "/images/curated/bellevue-teatret-1024.jpg",
    "cover_photographer": "Hansjorn",
    "cover_license": "CC BY-SA 3.0",
    "cover_source_url": "https://commons.wikimedia.org/wiki/File:Arnje_Jacobsen_Bellevue_Teater_2005-01.jpg"
  },
  "biblioteca-comunale-centrale-antonio-tiraboschi": {
    "cover_url": "/images/curated/biblioteca-comunale-centrale-antonio-tiraboschi-1024.jpg",
    "cover_photographer": "Barbaragerosa",
    "cover_license": "CC BY-SA 4.0",
    "cover_source_url": "https://commons.wikimedia.org/wiki/File:Bergamo_-_Biblioteca_comunale_centrale_%22Antonio_Tiraboschi%22_di_Bergamo_-_2024-09-06_19-42-41_001.jpg"
  },
  "bianchi-house": {
    "cover_url": "/images/curated/bianchi-house-1024.jpg",
    "cover_photographer": "EMCARQUITECTURA",
    "cover_license": "CC BY-SA 4.0",
    "cover_source_url": "https://commons.wikimedia.org/wiki/File:%CE%9A%CE%B1%CF%84%CE%BF%CE%B9%CE%BA%CE%AF%CE%B1_%CE%9C%CF%80%CE%B9%CE%AC%CE%BD%CF%84%CF%83%CE%B9_(Bianchi_House).jpg"
  },
  "blue-condominium": {
    "cover_url": "/images/curated/blue-condominium-1024.jpg",
    "cover_photographer": "Beyond My Ken",
    "cover_license": "CC BY-SA 4.0",
    "cover_source_url": "https://commons.wikimedia.org/wiki/File:105_Norfolk_Street_as_seen_from_Broome_Street.jpg"
  },
  "biblioteca-municipal-de-viana-do": {
    "cover_url": "/images/curated/biblioteca-municipal-de-viana-do-1024.jpg",
    "cover_photographer": "http://translatewiki.net/wiki/User:Pjcaldeira",
    "cover_license": "CC BY-SA 3.0",
    "cover_source_url": "https://commons.wikimedia.org/wiki/File:Biblioteca_de_Viana_do_Castelo.JPG"
  },
  "bodmer-foundation": {
    "cover_url": "/images/curated/bodmer-foundation-1024.jpg",
    "cover_photographer": "Romano1246",
    "cover_license": "CC BY-SA 3.0",
    "cover_source_url": "https://commons.wikimedia.org/wiki/File:Bodmer_Cologny_1.jpg"
  },
  "blue-front-shibaura": {
    "cover_url": "/images/curated/blue-front-shibaura-1024.jpg",
    "cover_photographer": "番記者",
    "cover_license": "CC0",
    "cover_source_url": "https://commons.wikimedia.org/wiki/File:BLUE_FRONT_SHIBAURA_entrance_obje_01.jpg"
  },
  "bordeaux-courthouse": {
    "cover_url": "/images/curated/bordeaux-courthouse-1024.jpg",
    "cover_photographer": "Zairon",
    "cover_license": "CC BY-SA 4.0",
    "cover_source_url": "https://commons.wikimedia.org/wiki/File:Bordeaux_Cath%C3%A9drale_Saint-Andr%C3%A9_Tour_Pey-Berland_Vue_sur_le_Palais_de_Justice.jpg"
  },
  "bonjour-tristesse": {
    "cover_url": "/images/curated/bonjour-tristesse-1024.jpg",
    "cover_photographer": "Georg Slickers",
    "cover_license": "CC BY-SA 3.0",
    "cover_source_url": "https://commons.wikimedia.org/wiki/File:Berlin_schlesische-str-7_bonjour-tristesse_20050224_p1010029.jpg"
  },
  "brasilia-cathedral": {
    "cover_url": "/images/curated/brasilia-cathedral-1024.jpg",
    "cover_photographer": "Agência Brasil",
    "cover_license": "CC BY-SA 3.0",
    "cover_source_url": "https://commons.wikimedia.org/wiki/File:Catedral_Metropolitana_de_Bras%C3%ADlia.jpg"
  },
  "botta-building-basel": {
    "cover_url": "/images/curated/botta-building-basel-1024.jpg",
    "cover_photographer": "Fred Romero from Paris, France",
    "cover_license": "CC BY 2.0",
    "cover_source_url": "https://commons.wikimedia.org/wiki/File:Basel_-_Bank_f%C3%BCr_Internationalen_Zahlungsausgleich-Botta_Building_(27527232812).jpg"
  },
  "brion-tomb": {
    "cover_url": "/images/curated/brion-tomb-1024.jpg",
    "cover_photographer": "Filippo Poli",
    "cover_license": "CC BY-SA 4.0",
    "cover_source_url": "https://commons.wikimedia.org/wiki/File:04_Tomba_Brion_-_San_Vito_d%27Altivole,_Treviso,_Italy_-_Carlo_Scarpa-FPPL3045.jpg"
  },
  "bridge-of-peace": {
    "cover_url": "/images/curated/bridge-of-peace-1024.jpg",
    "cover_photographer": "Uwe Brodrecht",
    "cover_license": "CC BY-SA 2.0",
    "cover_source_url": "https://commons.wikimedia.org/wiki/File:0077_-_Kaukasus_2014_-_Georgien.jpg"
  },
  "buro-und-geschaftshaus": {
    "cover_url": "/images/curated/buro-und-geschaftshaus-1024.jpg",
    "cover_photographer": "Frank Vincentz",
    "cover_license": "CC BY-SA 3.0",
    "cover_source_url": "https://commons.wikimedia.org/wiki/File:D%C3%BCsseldorf_-_Am_Handelshafen_-_Kaistra%C3%9Fe18_01_ies.jpg"
  },
  "c-v-starr-east-asian": {
    "cover_url": "/images/curated/c-v-starr-east-asian-1024.jpg",
    "cover_photographer": "Shunchosai Takehara Nobushige",
    "cover_license": "Public domain",
    "cover_source_url": "https://commons.wikimedia.org/wiki/File:%22A_Tour_Guide_to_the_Famous_Places_of_the_Capital%22_from_Akizato_Rito%27s_Miyako_meisho_zue_(1787).jpg"
  },
  "cais-das-artes": {
    "cover_url": "/images/curated/cais-das-artes-1024.jpg",
    "cover_photographer": "José Almeida Silveira",
    "cover_license": "CC BY-SA 4.0",
    "cover_source_url": "https://commons.wikimedia.org/wiki/File:Cais_das_Artes_1.jpg"
  },
  "campus-palmas-altas-sevilla": {
    "cover_url": "/images/curated/campus-palmas-altas-sevilla-1024.jpg",
    "cover_photographer": "CarlosVdeHabsburgo",
    "cover_license": "CC BY-SA 4.0",
    "cover_source_url": "https://commons.wikimedia.org/wiki/File:Campus_Palmas_Altas.jpg"
  },
  "can-lis": {
    "cover_url": "/images/curated/can-lis-1024.jpg",
    "cover_photographer": "Frans Drewniak",
    "cover_license": "CC BY-SA 2.0",
    "cover_source_url": "https://commons.wikimedia.org/wiki/File:Can_Lis2.jpg"
  },
  "capita-centre": {
    "cover_url": "/images/curated/capita-centre-1024.jpg",
    "cover_photographer": "EditorJ16",
    "cover_license": "CC BY-SA 4.0",
    "cover_source_url": "https://commons.wikimedia.org/wiki/File:9_Castlereagh_Street_Sydney.jpg"
  },
  "carlos-ramos-pavilion": {
    "cover_url": "/images/curated/carlos-ramos-pavilion-1024.jpg",
    "cover_photographer": "Leon from Taipei, Taiwan",
    "cover_license": "CC BY 2.0",
    "cover_source_url": "https://commons.wikimedia.org/wiki/File:Faculdade_de_Arquitectura_da_Universidade_do_Porto._(6085858281).jpg"
  },
  "carlton-hotel": {
    "cover_url": "/images/curated/carlton-hotel-1024.jpg",
    "cover_photographer": "Hmvh",
    "cover_license": "CC BY-SA 4.0",
    "cover_source_url": "https://commons.wikimedia.org/wiki/File:CHscene1973.jpg"
  },
  "casa-batllo": {
    "cover_url": "/images/curated/casa-batllo-1024.jpg",
    "cover_photographer": "Bernard Gagnon",
    "cover_license": "CC BY-SA 3.0",
    "cover_source_url": "https://commons.wikimedia.org/wiki/File:Casa_Batllo_01.jpg"
  },
  "casa-comolli-rustici": {
    "cover_url": "/images/curated/casa-comolli-rustici-1024.jpg",
    "cover_photographer": "Arbalete",
    "cover_license": "CC BY-SA 4.0",
    "cover_source_url": "https://commons.wikimedia.org/wiki/File:Milano_-_Casa_Comolli-Rustici_-_Vista_frontale.jpg"
  },
  "casa-das-historias-paula-rego": {
    "cover_url": "/images/curated/casa-das-historias-paula-rego-1024.jpg",
    "cover_photographer": "Pedro Ribeiro Simões from Lisboa, Portugal",
    "cover_license": "CC BY 2.0",
    "cover_source_url": "https://commons.wikimedia.org/wiki/File:%22Casa_das_Est%C3%B3rias%22_(Paula_Rego%27s_Museum)_(7571197386).jpg"
  },
  "casa-de-cha-da-boa": {
    "cover_url": "/images/curated/casa-de-cha-da-boa-1024.jpg",
    "cover_photographer": "Wikimaster919",
    "cover_license": "CC BY-SA 4.0",
    "cover_source_url": "https://commons.wikimedia.org/wiki/File:Casa_de_ch%C3%A1_da_boa_nova.jpg"
  },
  "casa-do-benin": {
    "cover_url": "/images/curated/casa-do-benin-1024.jpg",
    "cover_photographer": "Friduxa",
    "cover_license": "CC BY-SA 4.0",
    "cover_source_url": "https://commons.wikimedia.org/wiki/File:Abomey-Casa_do_Benin.jpg"
  },
  "casa-gilardi": {
    "cover_url": "/images/curated/casa-gilardi-1024.jpg",
    "cover_photographer": "Arudana",
    "cover_license": "CC BY-SA 4.0",
    "cover_source_url": "https://commons.wikimedia.org/wiki/File:Casa_gilardi.jpg"
  },
  "casa-lavezzari": {
    "cover_url": "/images/curated/casa-lavezzari-1024.jpg",
    "cover_photographer": "Arbalete",
    "cover_license": "CC BY-SA 4.0",
    "cover_source_url": "https://commons.wikimedia.org/wiki/File:Milano_casa_Lavezzari_scorcio.JPG"
  },
  "casa-pedraglio": {
    "cover_url": "/images/curated/casa-pedraglio-1024.jpg",
    "cover_photographer": "Naruto9393",
    "cover_license": "Public domain",
    "cover_source_url": "https://commons.wikimedia.org/wiki/File:Casa_pedraglio.jpg"
  },
  "casa-roberto-ivens-casa": {
    "cover_url": "/images/curated/casa-roberto-ivens-casa-1024.jpg",
    "cover_photographer": "Filipa Guimarães",
    "cover_license": "CC BY-SA 4.0",
    "cover_source_url": "https://commons.wikimedia.org/wiki/File:Casa_Roberto_Ivens.jpg"
  },
  "casino-di-campione": {
    "cover_url": "/images/curated/casino-di-campione-1024.jpg",
    "cover_photographer": "Chris j wood",
    "cover_license": "CC BY-SA 3.0",
    "cover_source_url": "https://commons.wikimedia.org/wiki/File:Campione_d%27Italia_03.jpg"
  },
  "cenotaph-for-the-a-bomb-victims": {
    "cover_url": "/images/curated/cenotaph-for-the-a-bomb-victims-1024.jpg",
    "cover_photographer": "RuinDig/Yuki Uchida",
    "cover_license": "CC BY 4.0",
    "cover_source_url": "https://commons.wikimedia.org/wiki/File:036_Hiroshima-Japan_2008-10.jpg"
  },
  "celine-and-heiner-bastian-exhibition": {
    "cover_url": "/images/curated/celine-and-heiner-bastian-exhibition-1024.jpg",
    "cover_photographer": "Gunnar Klack",
    "cover_license": "CC BY-SA 4.0",
    "cover_source_url": "https://commons.wikimedia.org/wiki/File:2006-12-Haus-Bastian-im-Bau.jpg"
  },
  "center-of-innovation-anacleto-angelini": {
    "cover_url": "/images/curated/center-of-innovation-anacleto-angelini-1024.jpg",
    "cover_photographer": "Carlos Figueroa Rojas",
    "cover_license": "CC BY-SA 4.0",
    "cover_source_url": "https://commons.wikimedia.org/wiki/File:Centro_de_Innovaci%C3%B3n_UC_Anacleto_Angelini,_Campus_San_Joaqu%C3%ADn_PUC,_Macul,_Santiago_20241108.jpg"
  },
  "central-library-des-moines": {
    "cover_url": "/images/curated/central-library-des-moines-1024.jpg",
    "cover_photographer": "Ljwnoble",
    "cover_license": "CC BY-SA 3.0",
    "cover_source_url": "https://commons.wikimedia.org/wiki/File:Central_Branch,_Des_Moines_Public_Library.jpg"
  },
  "centre-georges-pompidou": {
    "cover_url": "/images/curated/centre-georges-pompidou-1024.jpg",
    "cover_photographer": "RG72",
    "cover_license": "CC BY-SA 4.0",
    "cover_source_url": "https://commons.wikimedia.org/wiki/File:Apud_la_Centro_Georges-Pompidou.jpg"
  },
  "ceremonial-palace-of-georgia": {
    "cover_url": "/images/curated/ceremonial-palace-of-georgia-1024.jpg",
    "cover_photographer": "Marcin Konsek",
    "cover_license": "CC BY-SA 4.0",
    "cover_source_url": "https://commons.wikimedia.org/wiki/File:2014_Tbilisi,_Widok_z_Mostu_Pokoju_na_rzek%C4%99_Kura_i_jej_okolice_(05).jpg"
  },
  "chiesa-del-santo-volto": {
    "cover_url": "/images/curated/chiesa-del-santo-volto-1024.jpg",
    "cover_photographer": "SetteTreSette",
    "cover_license": "CC BY-SA 4.0",
    "cover_source_url": "https://commons.wikimedia.org/wiki/File:Chiesa_del_Santo_Volto,_Turin,_Italy.jpg"
  },
  "chiesa-di-nostra-signora-del": {
    "cover_url": "/images/curated/chiesa-di-nostra-signora-del-1024.jpg",
    "cover_photographer": "Pittirì",
    "cover_license": "CC BY-SA 4.0",
    "cover_source_url": "https://commons.wikimedia.org/wiki/File:Chiesa_di_Nostra_Signora_del_Cadore.jpg"
  },
  "church-of-cristo-obrero-y": {
    "cover_url": "/images/curated/church-of-cristo-obrero-y-1024.jpg",
    "cover_photographer": "Gonzalo 96",
    "cover_license": "CC BY-SA 4.0",
    "cover_source_url": "https://commons.wikimedia.org/wiki/File:Planta_Iglesia_Cristo_Obrero.jpg"
  },
  "church-of-nuestra-senora-de": {
    "cover_url": "/images/curated/church-of-nuestra-senora-de-1024.jpg",
    "cover_photographer": "Asqueladd",
    "cover_license": "CC BY-SA 3.0",
    "cover_source_url": "https://commons.wikimedia.org/wiki/File:Iglesia_de_los_Mexicanos.JPG"
  },
  "church-of-san-juan-de": {
    "cover_url": "/images/curated/church-of-san-juan-de-1024.jpg",
    "cover_photographer": "M.Peinado from Alcalá de Henares, España",
    "cover_license": "CC BY 2.0",
    "cover_source_url": "https://commons.wikimedia.org/wiki/File:000266_-_Alcal%C3%A1_de_Henares_(2689124351).jpg"
  },
  "chusanren-building-main-building": {
    "cover_url": "/images/curated/chusanren-building-main-building-1024.jpg",
    "cover_photographer": "Asturio Cantabrio",
    "cover_license": "CC BY-SA 4.0",
    "cover_source_url": "https://commons.wikimedia.org/wiki/File:Aitatehaku_Chusanren_Building_2023-11_ac_(1).jpg"
  },
  "church-of-the-three-crosses": {
    "cover_url": "/images/curated/church-of-the-three-crosses-1024.jpg",
    "cover_photographer": "Sino Yu",
    "cover_license": "CC BY-SA 4.0",
    "cover_source_url": "https://commons.wikimedia.org/wiki/File:Church_of_the_Three_Crosses_20200627_01.jpg"
  },
  "cidade-das-artes-bibi-ferreira": {
    "cover_url": "/images/curated/cidade-das-artes-bibi-ferreira-1024.jpg",
    "cover_photographer": "João Antônio SV",
    "cover_license": "CC BY 4.0",
    "cover_source_url": "https://commons.wikimedia.org/wiki/File:2016-08-27_-_Cidade_da_M%C3%BAsica.jpg"
  },
  "cite-de-locean-et-du": {
    "cover_url": "/images/curated/cite-de-locean-et-du-1024.jpg",
    "cover_photographer": "Arno8892",
    "cover_license": "CC BY-SA 4.0",
    "cover_source_url": "https://commons.wikimedia.org/wiki/File:Cit%C3%A9_de_l%27oc%C3%A9an_Biarritz.jpg"
  },
  "ciutat-de-la-justicia-de": {
    "cover_url": "/images/curated/ciutat-de-la-justicia-de-1024.jpg",
    "cover_photographer": "Enric",
    "cover_license": "CC BY 4.0",
    "cover_source_url": "https://commons.wikimedia.org/wiki/File:33_Ciutat_de_la_Just%C3%ADcia,_des_de_l%27avinguda_de_la_Granvia_de_l%27Hospitalet.jpg"
  },
  "city-center-towers-complex": {
    "cover_url": "/images/curated/city-center-towers-complex-1024.jpg",
    "cover_photographer": "Sahmeditor",
    "cover_license": "Public domain",
    "cover_source_url": "https://commons.wikimedia.org/wiki/File:City_Center_Towers_FW.JPG"
  },
  "cleveland-museum-of-art": {
    "cover_url": "/images/curated/cleveland-museum-of-art-1024.jpg",
    "cover_photographer": "Tim Evanson from Cleveland Heights, Ohio, USA",
    "cover_license": "CC BY-SA 2.0",
    "cover_source_url": "https://commons.wikimedia.org/wiki/File:ArtLens_teens_-_Cleveland_Museum_of_Art_(41439990454).jpg"
  },
  "cleveland-museum-of-art-building": {
    "cover_url": "/images/curated/cleveland-museum-of-art-building-1024.jpg",
    "cover_photographer": "Tim Evanson from Cleveland Heights, Ohio, USA",
    "cover_license": "CC BY-SA 2.0",
    "cover_source_url": "https://commons.wikimedia.org/wiki/File:ArtLens_teens_-_Cleveland_Museum_of_Art_(41439990454).jpg"
  },
  "coleccion-jumex": {
    "cover_url": "/images/curated/coleccion-jumex-1024.jpg",
    "cover_photographer": "Nan Palmero from San Antonio, TX, USA",
    "cover_license": "CC BY 2.0",
    "cover_source_url": "https://commons.wikimedia.org/wiki/File:Camel_and_Carrot_at_Museo_Jumex_(25725509267).jpg"
  },
  "col-legi-darquitectes": {
    "cover_url": "/images/curated/col-legi-darquitectes-1024.jpg",
    "cover_photographer": "Jordi Gili",
    "cover_license": "CC BY-SA 4.0",
    "cover_source_url": "https://commons.wikimedia.org/wiki/File:Col%C2%B7legi_d%27Arquitectes_(Tarragona)_01.jpg"
  },
  "coliseu-de-viana-do-castelo": {
    "cover_url": "/images/curated/coliseu-de-viana-do-castelo-1024.jpg",
    "cover_photographer": "Joseolgon",
    "cover_license": "CC BY-SA 4.0",
    "cover_source_url": "https://commons.wikimedia.org/wiki/File:Centro_Cultural_de_Viana_do_Castelo_(1).jpg"
  },
  "college-of-education-training-school": {
    "cover_url": "/images/curated/college-of-education-training-school-1024.jpg",
    "cover_photographer": "Tiia Monto",
    "cover_license": "CC BY-SA 4.0",
    "cover_source_url": "https://commons.wikimedia.org/wiki/File:JYU_-_Proxima.jpg"
  },
  "columbushaus": {
    "cover_url": "/images/curated/columbushaus-1024.jpg",
    "cover_photographer": "Foto: Wschmock",
    "cover_license": "Public domain",
    "cover_source_url": "https://commons.wikimedia.org/wiki/File:Potsdamer-Platz-1-1954.jpg"
  },
  "cyclorama-building": {
    "cover_url": "/images/curated/cyclorama-building-1024.jpg",
    "cover_photographer": "Fæ",
    "cover_license": "Public domain",
    "cover_source_url": "https://commons.wikimedia.org/wiki/File:Cyclorama_Building,_125_Taneytown_Road,_Gettysburg,_Adams_County,_PA_HABS_PA-6709_(sheet_10_of_24).png"
  },
  "crawford-manor": {
    "cover_url": "/images/curated/crawford-manor-1024.jpg",
    "cover_photographer": "ajay_suresh",
    "cover_license": "CC BY 2.0",
    "cover_source_url": "https://commons.wikimedia.org/wiki/File:Crawford_Manor_(54106345969).jpg"
  },
  "cymbalista-synagogue-and-jewish-heritage": {
    "cover_url": "/images/curated/cymbalista-synagogue-and-jewish-heritage-1024.jpg",
    "cover_photographer": "ברוך ניב",
    "cover_license": "CC BY 2.5",
    "cover_source_url": "https://commons.wikimedia.org/wiki/File:120255_zimbalista_synagogue_and_center_for_jewish_heritag_PikiWiki_Israel.jpg"
  },
  "danish-national-bank": {
    "cover_url": "/images/curated/danish-national-bank-1024.jpg",
    "cover_photographer": "cjreddaway",
    "cover_license": "CC BY 2.0",
    "cover_source_url": "https://commons.wikimedia.org/wiki/File:110914_Jacobsen_Danish_National_Bank_00_(7000199966).jpg"
  },
  "dar-al-islam": {
    "cover_url": "/images/curated/dar-al-islam-1024.jpg",
    "cover_photographer": "Jared Tarbell from Awesometown, United States of America",
    "cover_license": "CC BY 2.0",
    "cover_source_url": "https://commons.wikimedia.org/wiki/File:Dar_al_Islam_Mosque_(352480000).jpg"
  },
  "de-bijenkorf": {
    "cover_url": "/images/curated/de-bijenkorf-1024.jpg",
    "cover_photographer": "Kris Roderburg",
    "cover_license": "CC BY-SA 4.0",
    "cover_source_url": "https://commons.wikimedia.org/wiki/File:Bekleding_pilaar_-_Rotterdam_-_20533913_-_RCE.jpg"
  },
  "de-citadel": {
    "cover_url": "/images/curated/de-citadel-1024.jpg",
    "cover_photographer": "Stipo team",
    "cover_license": "CC BY-SA 2.0",
    "cover_source_url": "https://commons.wikimedia.org/wiki/File:Citadel_almere_flickr.jpg"
  },
  "de-la-warr-pavilion": {
    "cover_url": "/images/curated/de-la-warr-pavilion-1024.jpg",
    "cover_photographer": "Phil Sellens from East Sussex",
    "cover_license": "CC BY 2.0",
    "cover_source_url": "https://commons.wikimedia.org/wiki/File:The_De_La_Warr_Pavilion_%26_The_Collonade,_Bexhill_on_sea._c._late_1930s_(8278266714).jpg"
  },
  "dentsu-tsukiji-building": {
    "cover_url": "/images/curated/dentsu-tsukiji-building-1024.jpg",
    "cover_photographer": "Yu Morita",
    "cover_license": "CC BY-SA 2.0",
    "cover_source_url": "https://commons.wikimedia.org/wiki/File:Dentsu_Tec.jpg"
  },
  "dulles-airport": {
    "cover_url": "/images/curated/dulles-airport-1024.jpg",
    "cover_photographer": "Joe Ravi",
    "cover_license": "CC BY-SA 3.0",
    "cover_source_url": "https://commons.wikimedia.org/wiki/File:Washington_Dulles_International_Airport_main_terminal.jpg"
  },
  "dortmund-city-and-state-library": {
    "cover_url": "/images/curated/dortmund-city-and-state-library-1024.jpg",
    "cover_photographer": "Libman06",
    "cover_license": "CC BY-SA 4.0",
    "cover_source_url": "https://commons.wikimedia.org/wiki/File:2015_Lesesaal_2OG_(3).JPG"
  },
  "edifici-illa-diagonal": {
    "cover_url": "/images/curated/edifici-illa-diagonal-1024.jpg",
    "cover_photographer": "Enfo",
    "cover_license": "CC BY-SA 3.0",
    "cover_source_url": "https://commons.wikimedia.org/wiki/File:120_Edifici_L%27Illa,_av._Diagonal.jpg"
  },
  "elementary-school": {
    "cover_url": "/images/curated/elementary-school-1024.jpg",
    "cover_photographer": "Helge Fahrnberger / www.helge.at",
    "cover_license": "CC BY-SA 3.0",
    "cover_source_url": "https://commons.wikimedia.org/wiki/File:Gando-School-Burkina-Faso.JPG"
  },
  "estadio-municipal-de-braga": {
    "cover_url": "/images/curated/estadio-municipal-de-braga-1024.jpg",
    "cover_photographer": "Joseolgon",
    "cover_license": "CC BY-SA 4.0",
    "cover_source_url": "https://commons.wikimedia.org/wiki/File:Academia_do_SCB_(1).jpg"
  },
  "ensemble-of-alvaro-sizas-architecture": {
    "cover_url": "/images/curated/ensemble-of-alvaro-sizas-architecture-1024.jpg",
    "cover_photographer": "trevor.patt from Lausanne, Switzerland",
    "cover_license": "CC BY-SA 2.0",
    "cover_source_url": "https://commons.wikimedia.org/wiki/File:Banco_Borges_e_Irm%C3%A3o_Vila_do_Conde_2011.jpg"
  },
  "european-court-of-human-rights": {
    "cover_url": "/images/curated/european-court-of-human-rights-1024.jpg",
    "cover_photographer": "Jeuwre",
    "cover_license": "CC BY-SA 4.0",
    "cover_source_url": "https://commons.wikimedia.org/wiki/File:De-Europ%C3%A4ischer_Gerichtshof_f%C3%BCr_Menschenrechte.ogg"
  },
  "estadio-serra-dourada": {
    "cover_url": "/images/curated/estadio-serra-dourada-1024.jpg",
    "cover_photographer": "Ev. Alexandry Silva",
    "cover_license": "CC BY-SA 3.0",
    "cover_source_url": "https://commons.wikimedia.org/wiki/File:Est%C3%A1dio_Serra_Dourada_-_panoramio_(1).jpg"
  },
  "expo-70-pavilion": {
    "cover_url": "/images/curated/expo-70-pavilion-1024.jpg",
    "cover_photographer": "663highland",
    "cover_license": "CC BY 2.5",
    "cover_source_url": "https://commons.wikimedia.org/wiki/File:131116_Expo_Commemoration_Park_Suita_Osaka_pref_Japan46s3.jpg"
  },
  "facultad-de-ciencias-de-la": {
    "cover_url": "/images/curated/facultad-de-ciencias-de-la-1024.jpg",
    "cover_photographer": "User:Lansbricae",
    "cover_license": "CC BY-SA 3.0",
    "cover_source_url": "https://commons.wikimedia.org/wiki/File:Facultade_de_Xornalismo_USC_Alvaro_Siza.JPG"
  },
  "fcg-building": {
    "cover_url": "/images/curated/fcg-building-1024.jpg",
    "cover_photographer": "Hiroyuki Sato",
    "cover_license": "CC BY-SA 3.0",
    "cover_source_url": "https://commons.wikimedia.org/wiki/File:1_Chome-4_Daiba,_Minato-ku,_T%C5%8Dky%C5%8D-to_135-0091,_Japan_-_panoramio_(4).jpg"
  },
  "finlandia-hall": {
    "cover_url": "/images/curated/finlandia-hall-1024.jpg",
    "cover_photographer": "Thermos",
    "cover_license": "CC BY-SA 3.0",
    "cover_source_url": "https://commons.wikimedia.org/wiki/File:Finlandia_Wiki.jpg"
  },
  "ferry-house": {
    "cover_url": "/images/curated/ferry-house-1024.jpg",
    "cover_photographer": "Collin Knopp-Schwyn",
    "cover_license": "CC BY 4.0",
    "cover_source_url": "https://commons.wikimedia.org/wiki/File:Dexter_M._Ferry_Cooperative_House,_August_2014.jpg"
  },
  "finnish-pavilion": {
    "cover_url": "/images/curated/finnish-pavilion-1024.jpg",
    "cover_photographer": "Gerda Arendt",
    "cover_license": "CC0",
    "cover_source_url": "https://commons.wikimedia.org/wiki/File:60th_Venice_Biennale,_Finnish_pavilion.jpg"
  },
  "fiore-di-botta": {
    "cover_url": "/images/curated/fiore-di-botta-1024.jpg",
    "cover_photographer": "Mattiniero70",
    "cover_license": "CC BY-SA 4.0",
    "cover_source_url": "https://commons.wikimedia.org/wiki/File:DSC_6587_fiore_di_botta.jpg"
  },
  "flame-of-peace": {
    "cover_url": "/images/curated/flame-of-peace-1024.jpg",
    "cover_photographer": "RuinDig/Yuki Uchida",
    "cover_license": "CC BY 4.0",
    "cover_source_url": "https://commons.wikimedia.org/wiki/File:034_Hiroshima-Japan_2008-10.jpg"
  },
  "five-scattered-houses-ningbo": {
    "cover_url": "/images/curated/five-scattered-houses-ningbo-1024.jpg",
    "cover_photographer": "Siyuwj",
    "cover_license": "CC BY-SA 3.0",
    "cover_source_url": "https://commons.wikimedia.org/wiki/File:Five_Scattered_Houses_in_Yinzhou_Park.svg"
  },
  "fondazione-querini-stampalia": {
    "cover_url": "/images/curated/fondazione-querini-stampalia-1024.jpg",
    "cover_photographer": "GattoCeliaco",
    "cover_license": "CC BY-SA 4.0",
    "cover_source_url": "https://commons.wikimedia.org/wiki/File:Affresco_della_volta_del_portego,_Palazzo_Qurini_Stampalia.jpg"
  },
  "florence-cathedral-dome": {
    "cover_url": "/images/curated/florence-cathedral-dome-1024.jpg",
    "cover_photographer": "Petar Milošević",
    "cover_license": "CC BY-SA 3.0",
    "cover_source_url": "https://commons.wikimedia.org/wiki/File:Florence_Duomo_from_Michelangelo_hill.jpg"
  },
  "footbridge-of-the-science-museum": {
    "cover_url": "/images/curated/footbridge-of-the-science-museum-1024.jpg",
    "cover_photographer": "Ruben Ortega",
    "cover_license": "CC BY-SA 4.0",
    "cover_source_url": "https://commons.wikimedia.org/wiki/File:Pasarela_del_Museo_de_la_Ciencia_de_Valladolid_desde_la_torre_del_Museo.JPG"
  },
  "forum-castrop-rauxel": {
    "cover_url": "/images/curated/forum-castrop-rauxel-1024.jpg",
    "cover_photographer": "Gunnar Klack",
    "cover_license": "CC BY-SA 4.0",
    "cover_source_url": "https://commons.wikimedia.org/wiki/File:2021-11-03-Forum-Castrop-Rauxel-05.jpg"
  },
  "former-weichmanns-textile-house": {
    "cover_url": "/images/curated/former-weichmanns-textile-house-1024.jpg",
    "cover_photographer": "Ebielmaj",
    "cover_license": "CC BY-SA 3.0 pl",
    "cover_source_url": "https://commons.wikimedia.org/wiki/File:Bank_Polski_01.JPG"
  },
  "fredensborg-houses": {
    "cover_url": "/images/curated/fredensborg-houses-1024.jpg",
    "cover_photographer": "Ramblersen",
    "cover_license": "CC BY-SA 3.0",
    "cover_source_url": "https://commons.wikimedia.org/wiki/File:Fredensborg_Houses_-_central_module.jpg"
  },
  "french-embassy-building": {
    "cover_url": "/images/curated/french-embassy-building-1024.jpg",
    "cover_photographer": "Foto: Bernd Schwabe",
    "cover_license": "CC BY-SA 3.0",
    "cover_source_url": "https://commons.wikimedia.org/wiki/File:2015-01-11_Ambassade_de_France_Pariser_Platz_Berlin_Je_suis_Charlie_Franz%C3%B6sische_Botschaft.JPG"
  },
  "fukuoka-art-museum": {
    "cover_url": "/images/curated/fukuoka-art-museum-1024.jpg",
    "cover_photographer": "MK Products",
    "cover_license": "CC BY-SA 3.0",
    "cover_source_url": "https://commons.wikimedia.org/wiki/File:Fukuoka_Art_Museum_1.jpg"
  },
  "gateway-arch": {
    "cover_url": "/images/curated/gateway-arch-1024.jpg",
    "cover_photographer": "Daniel Schwen",
    "cover_license": "CC BY-SA 4.0",
    "cover_source_url": "https://commons.wikimedia.org/wiki/File:St_Louis_night_expblend.jpg"
  },
  "gilbey-house": {
    "cover_url": "/images/curated/gilbey-house-1024.jpg",
    "cover_photographer": "No Swan So Fine",
    "cover_license": "CC BY-SA 4.0",
    "cover_source_url": "https://commons.wikimedia.org/wiki/File:24-28_Oval_Road,_Camden_Town,_August_2022.jpg"
  },
  "glass-house": {
    "cover_url": "/images/curated/glass-house-1024.jpg",
    "cover_photographer": "Jrricky",
    "cover_license": "CC BY-SA 4.0",
    "cover_source_url": "https://commons.wikimedia.org/wiki/File:A_Casa_de_Vidro.jpg"
  },
  "grand-prince-hotel-akasaka": {
    "cover_url": "/images/curated/grand-prince-hotel-akasaka-1024.jpg",
    "cover_photographer": "BetacommandBot",
    "cover_license": "CC BY-SA 3.0",
    "cover_source_url": "https://commons.wikimedia.org/wiki/File:Akasaka_20061215_0053.jpg"
  },
  "groninger-museum-building": {
    "cover_url": "/images/curated/groninger-museum-building-1024.jpg",
    "cover_photographer": "Wutsje / Wikimedia Commons / CC-BY-SA 3.0",
    "cover_license": "CC BY-SA 3.0",
    "cover_source_url": "https://commons.wikimedia.org/wiki/File:20140614_Groninger_Museum_Groningen_NL.jpg"
  },
  "greenwich-hospital": {
    "cover_url": "/images/curated/greenwich-hospital-1024.jpg",
    "cover_photographer": "MRT",
    "cover_license": "CC BY-SA 4.0",
    "cover_source_url": "https://commons.wikimedia.org/wiki/File:Old_Royal_Naval_College_and_Queen%27s_House,_Greenwich_-_2021-10-30.jpg"
  },
  "guangzhou-opera-house": {
    "cover_url": "/images/curated/guangzhou-opera-house-1024.jpg",
    "cover_photographer": "GnuDoyng",
    "cover_license": "CC BY-SA 3.0",
    "cover_source_url": "https://commons.wikimedia.org/wiki/File:Guangzhou_Opera_House_overview.JPG"
  },
  "gropius-house": {
    "cover_url": "/images/curated/gropius-house-1024.jpg",
    "cover_photographer": "The original uploader was Daderot at English Wikipedia.",
    "cover_license": "CC BY-SA 3.0",
    "cover_source_url": "https://commons.wikimedia.org/wiki/File%3AGropius_House%2C_Lincoln%2C_Massachusetts_-_Front_View.JPG"
  },
  "hadassah-university-hospital-mt-scopus": {
    "cover_url": "/images/curated/hadassah-university-hospital-mt-scopus-1024.jpg",
    "cover_photographer": "zeevveez from Jerusalem, Israel",
    "cover_license": "CC BY 2.0",
    "cover_source_url": "https://commons.wikimedia.org/wiki/File:Building_Around_Trees-3_(4934071885).jpg"
  },
  "hampton-court": {
    "cover_url": "/images/curated/hampton-court-1024.jpg",
    "cover_photographer": null,
    "cover_license": "CC BY-SA",
    "cover_source_url": "https://upload.wikimedia.org/wikipedia/commons/0/0a/Hampton_Court_Palace.jpg/Hampton_Court_Palace.jpg"
  },
  "harting-vertriebsgebaude": {
    "cover_url": "/images/curated/harting-vertriebsgebaude-1024.jpg",
    "cover_photographer": "TUBS",
    "cover_license": "CC BY-SA 3.0",
    "cover_source_url": "https://commons.wikimedia.org/wiki/File:2010-05-21_Minden_Harting_(1).jpg"
  },
  "hashima-city-hall-1959-2022": {
    "cover_url": "/images/curated/hashima-city-hall-1959-2022-1024.jpg",
    "cover_photographer": "Asturio Cantabrio",
    "cover_license": "CC BY-SA 4.0",
    "cover_source_url": "https://commons.wikimedia.org/wiki/File:Hashima_City_Hall_2019-11_ac_(5).jpg"
  },
  "haus-am-checkpoint-charlie": {
    "cover_url": "/images/curated/haus-am-checkpoint-charlie-1024.jpg",
    "cover_photographer": "Gunnar Klack",
    "cover_license": "CC BY-SA 4.0",
    "cover_source_url": "https://commons.wikimedia.org/wiki/File:2000-05-Haus-am-Checkpoint-Charlie-IBA-87.jpg"
  },
  "hayashibara-museum-of-art": {
    "cover_url": "/images/curated/hayashibara-museum-of-art-1024.jpg",
    "cover_photographer": "663highland",
    "cover_license": "CC BY 2.5",
    "cover_source_url": "https://commons.wikimedia.org/wiki/File:160319_Hayashibara_Museum_of_Art_Okayama_Japan03n.jpg"
  },
  "haus-des-deutschen-metallarbeiterverbandes": {
    "cover_url": "/images/curated/haus-des-deutschen-metallarbeiterverbandes-1024.jpg",
    "cover_photographer": "Jörg Zägel",
    "cover_license": "CC BY-SA 3.0",
    "cover_source_url": "https://commons.wikimedia.org/wiki/File:Berlin,_Kreuzberg,_Alte_Jakobstrasse_148-149,_IG-Metall-Haus.jpg"
  },
  "ronchamp": {
    "cover_url": "https://upload.wikimedia.org/wikipedia/commons/1/16/Chapelle_Notre-Dame-du_Haut_05.jpg",
    "cover_photographer": "Unknown author",
    "cover_license": "Public domain",
    "cover_source_url": "https://commons.wikimedia.org/wiki/File:Chapelle_Notre-Dame-du_Haut_05.jpg"
  }
}